hermescloud/__init__.py
hermescloud/hermes.py
hermescloud/utils.py
hermescloud-0.0.2.dist-info/LICENSE
hermescloud-0.0.2.dist-info/METADATA
hermescloud-0.0.2.dist-info/WHEEL
hermescloud-0.0.2.dist-info/top_level.txt
hermescloud-0.0.2.dist-info/RECORD
