Metadata-Version: 2.1
Name: hermescloud
Version: 0.0.2
Summary: Extremely fast full-text-search algorithm and caching system
Home-page: https://github.com/realTristan/Hermes/cloud/wrappers/python
Author: Tristan Simpson
Author-email: heytristaann@gmail.com
Project-URL: Bug Tracker, https://github.com/realTristan/Hermes/issues
Classifier: Programming Language :: Python :: 3
Classifier: License :: OSI Approved :: MIT License
Classifier: Operating System :: OS Independent
Requires-Python: >=3.6
License-File: LICENSE
